safebooru/__init__.py
safebooru/safebooru.py
api_safebooru-0.0.1.dist-info/LICENSE
api_safebooru-0.0.1.dist-info/METADATA
api_safebooru-0.0.1.dist-info/WHEEL
api_safebooru-0.0.1.dist-info/top_level.txt
api_safebooru-0.0.1.dist-info/RECORD
