Metadata-Version: 2.1
Name: api-safebooru
Version: 0.0.1
Summary: A basic safebooru API wrapper module.
Home-page: https://github.com/sa-lad/safebooru/
Author: salad
Author-email: salad.devel@gmail.com
License: General Public License V3
Keywords: safebooru
Platform: UNKNOWN
Classifier: License :: OSI Approved :: GNU General Public License v3 (GPLv3)
Classifier: Intended Audience :: Developers
Classifier: Natural Language :: English
Classifier: Operating System :: OS Independent
Classifier: Topic :: Utilities
License-File: LICENSE
